smux.py
smux.py-0.1.21.data/scripts/smux.py
smux.py-0.1.21.dist-info/LICENSE
smux.py-0.1.21.dist-info/METADATA
smux.py-0.1.21.dist-info/WHEEL
smux.py-0.1.21.dist-info/top_level.txt
smux.py-0.1.21.dist-info/RECORD
