Metadata-Version: 2.1
Name: smux.py
Version: 0.1.21
Summary: Simple tmux launcher that will take less than 2 minutes to learn.
Home-page: https://github.com/hq6/smux
Author: Henry Qin
Author-email: root@hq6.me
License: MIT
Platform: All platforms that tmux runs on.
